{
  "users": [
    {
      "uid": "e2b73a2d-7ff1-4d70-8e52-b9f7a4ce94f6",
      "username": "IndokuDev",
      "password": "12345",
      "photo_profile": "",
      "created_at": 1698249211000
    },
    {
      "uid": "4b0b9055-61a6-45cf-bce1-bd54684c3a4d",
      "username": "udindindindun",
      "password": "123456",
      "photo_profile": "",
      "created_at": 1709038453000
    },
    {
      "uid": "ac037f83-1639-44e4-842a-0ddf4f8d9dfc",
      "username": "Crazy bro🔥🔥",
      "password": "orgil",
      "photo_profile": "",
      "created_at": 1721102385000
    },
    {
      "uid": "8cb6dd64-9783-4e58-a7c4-35b2dbe419ff",
      "username": "Ahmad Raghib",
      "password": "12345",
      "photo_profile": "",
      "created_at": 1712321024000
    },
    {
      "uid": "56e59d0e-f2e4-41f0-8772-bf92f49198b7",
      "username": "Dimas",
      "password": "12345",
      "photo_profile": "",
      "created_at": 1693725419000
    },
    {
      "uid": "be1983aa-bbb0-4d57-b83c-dae6ab62f8a1",
      "username": "Mama lemon",
      "password": "123",
      "photo_profile": "",
      "created_at": 1700123456000
    },
    {
      "uid": "fd8c65b0-91c2-4c5f-a43c-ef4055b918ff",
      "username": "Ahmad",
      "password": "12345",
      "photo_profile": "",
      "created_at": 1725427879000
    }
  ],
  "chats": [
    {
      "from": "IndokuDev",
      "to": "udindindindun",
      "message": "halo",
      "timestamp": 1751796682005
    },
    {
      "from": "udindindindun",
      "to": "IndokuDev",
      "message": "Lu kek kontol",
      "timestamp": 1751797122046
    },
    {
      "from": "IndokuDev",
      "to": "udindindindun",
      "message": "anjing juga lu",
      "timestamp": 1751797166446
    },
    {
      "from": "udindindindun",
      "to": "IndokuDev",
      "message": "Bacot",
      "timestamp": 1751797193934
    },
    {
      "from": "udindindindun",
      "to": "IndokuDev",
      "message": "Mwueheheheheh",
      "timestamp": 1751797208310
    },
    {
      "from": "IndokuDev",
      "to": "udindindindun",
      "message": "ngentot",
      "timestamp": 1751797261284
    },
    {
      "from": "udindindindun",
      "to": "IndokuDev",
      "message": "Lah njir",
      "timestamp": 1751797289607
    },
    {
      "from": "IndokuDev",
      "to": "udindindindun",
      "message": "woy kontol",
      "timestamp": 1751797806301
    },
    {
      "from": "udindindindun",
      "to": "IndokuDev",
      "message": "apa babi",
      "timestamp": 1751797823171
    },
    {
      "from": "IndokuDev",
      "to": "udindindindun",
      "message": "apa ngentot!",
      "timestamp": 1751797844750
    },
    {
      "from": "udindindindun",
      "to": "IndokuDev",
      "message": "woy!",
      "timestamp": 1751797853669
    },
    {
      "from": "IndokuDev",
      "to": "udindindindun",
      "message": "woy",
      "timestamp": 1751797979932
    },
    {
      "from": "udindindindun",
      "to": "IndokuDev",
      "message": "anjing",
      "timestamp": 1751798017800
    },
    {
      "from": "udindindindun",
      "to": "IndokuDev",
      "message": "woy",
      "timestamp": 1751798027978
    },
    {
      "from": "udindindindun",
      "to": "IndokuDev",
      "message": "p",
      "timestamp": 1751798030246
    },
    {
      "from": "udindindindun",
      "to": "IndokuDev",
      "message": "\u003Cbold\u003E\u003Canjay\u003E",
      "timestamp": 1751798045602
    },
    {
      "from": "udindindindun",
      "to": "IndokuDev",
      "message": "woy memek",
      "timestamp": 1751798136275
    },
    {
      "from": "udindindindun",
      "to": "IndokuDev",
      "message": "Kobtol",
      "timestamp": 1751798161613
    },
    {
      "from": "udindindindun",
      "to": "IndokuDev",
      "message": "I said a kontol sama lo semua",
      "timestamp": 1751798194499
    },
    {
      "from": "IndokuDev",
      "to": "udindindindun",
      "message": "kontol memek",
      "timestamp": 1751798930209
    },
    {
      "from": "IndokuDev",
      "to": "udindindindun",
      "message": "halo",
      "timestamp": 1751798956670
    },
    {
      "from": "IndokuDev",
      "to": "udindindindun",
      "message": "halo",
      "timestamp": 1751798970633
    },
    {
      "from": "udindindindun",
      "to": "IndokuDev",
      "message": "Hai",
      "timestamp": 1751798996995
    },
    {
      "from": "udindindindun",
      "to": "IndokuDev",
      "message": "Megawati",
      "timestamp": 1751799011651
    },
    {
      "from": "IndokuDev",
      "to": "udindindindun",
      "message": "halo",
      "timestamp": 1751799015848
    },
    {
      "from": "udindindindun",
      "to": "IndokuDev",
      "message": "Hai",
      "timestamp": 1751799027693
    },
    {
      "from": "udindindindun",
      "to": "IndokuDev",
      "message": "Bembem",
      "timestamp": 1751799036677
    },
    {
      "from": "IndokuDev",
      "to": "udindindindun",
      "message": "kontol",
      "timestamp": 1751799213934
    },
    {
      "from": "IndokuDev",
      "to": "Crazy bro🔥🔥",
      "message": "woy kontol",
      "timestamp": 1751864139416
    },
    {
      "from": "Crazy bro🔥🔥",
      "to": "IndokuDev",
      "message": "Apa kontol",
      "timestamp": 1751864159285
    },
    {
      "from": "IndokuDev",
      "to": "Crazy bro🔥🔥",
      "message": "diam kontol",
      "timestamp": 1751864167435
    },
    {
      "from": "IndokuDev",
      "to": "Crazy bro🔥🔥",
      "message": "woy",
      "timestamp": 1751865531038
    },
    {
      "from": "Ahmad Raghib",
      "to": "IndokuDev",
      "message": "WOY MEMEK",
      "timestamp": 1751865892900
    },
    {
      "from": "Mama lemon",
      "to": "IndokuDev",
      "message": "Assalamualaikum",
      "timestamp": 1751874969870
    },
    {
      "from": "IndokuDev",
      "to": "Mama lemon",
      "message": "Apa?",
      "timestamp": 1751874998631
    },
    {
      "from": "IndokuDev",
      "to": "Mama lemon",
      "message": "Waalaikumsalam",
      "timestamp": 1751875012259
    },
    {
      "from": "IndokuDev",
      "to": "Mama lemon",
      "message": "Waalaikumsalam",
      "timestamp": 1751875012749
    },
    {
      "from": "IndokuDev",
      "to": "udindindindun",
      "message": "\u003Cb\u003EKontol\u003Cb\u003E",
      "timestamp": 1751876466443
    },
    {
      "from": "IndokuDev",
      "to": "udindindindun",
      "message": "Halo kontol",
      "timestamp": 1751881132807
    }
  ]
}